tg_api_gen/__init__.py
tg_api_gen/android_devices.txt
tg_api_gen-23.0.2.dist-info/METADATA
tg_api_gen-23.0.2.dist-info/WHEEL
tg_api_gen-23.0.2.dist-info/RECORD
